[
  {
    "id": "1",
    "name": "Modern blog",
    "type": "blog",
    "description": "Modern blog theme for VuePress.",
    "image": "/img/screenshots/modern-blog-2.jpeg",
    "github": "https://github.com/z3by/vuepress-theme-modern-blog",
    "link": "https://vp-modern.z3by.com/",
    "screenShots": [
      "/img/screenshots/modern-blog-1.jpeg",
      "/img/screenshots/modern-blog-2.jpeg",
      "/img/screenshots/modern-blog-3.jpeg",
      "/img/screenshots/modern-blog-4.jpeg",
      "/img/screenshots/modern-blog-5.jpeg"
    ]
  },
  {
    "id": "2",
    "name": "BriteCore",
    "type": "docs",
    "description": "BriteCore docs theme for Vuepress",
    "image": "/img/screenshots/britecore-1.jpeg",
    "github": "https://github.com/z3by/vuepress-theme-britecore",
    "link": "https://vp-britecore.z3by.com/",
    "screenShots": [
      "/img/screenshots/britecore-1.jpeg",
      "/img/screenshots/britecore-2.jpeg",
      "/img/screenshots/britecore-3.jpeg"
    ]
  },
  {
    "id": "3",
    "name": "Reco",
    "type": "docs",
    "description": "A simple and beautiful vuepress Blog & Doc theme.",
    "image": "/img/screenshots/reco-1.jpeg",
    "github": "https://github.com/vuepress-reco/vuepress-theme-reco",
    "link": "https://vuepress-theme-reco.recoluan.com/",
    "screenShots": [
      "/img/screenshots/reco-1.jpeg",
      "/img/screenshots/reco-2.jpeg"
    ]
  },
  {
    "id": "4",
    "name": "Egoist",
    "type": "blog",
    "description": "A simple and beautiful vuepress Blog & Doc theme.",
    "image": "/img/screenshots/egoist-1.jpeg",
    "github": "https://github.com/ulivz/vuepress-theme-egoist",
    "link": "https://egoist.ulivz.com/",
    "screenShots": [
      "/img/screenshots/egoist-1.jpeg",
      "/img/screenshots/egoist-2.jpeg",
      "/img/screenshots/egoist-3.jpeg"
    ]
  },
  {
    "id": "5",
    "name": "yubisaki",
    "type": "blog",
    "description": "A blog theme for vuepress",
    "image": "/img/screenshots/yubisaki-3.jpeg",
    "github": "https://github.com/Yubisaki/vuepress-theme-yubisaki",
    "link": "https://wuwaki.me/yubisaki/intro.html",
    "screenShots": [
      "/img/screenshots/yubisaki-1.jpeg",
      "/img/screenshots/yubisaki-2.jpeg",
      "/img/screenshots/yubisaki-3.jpeg"
    ]
  },
  {
    "id": "6",
    "name": "meteorlxy",
    "type": "blog",
    "description": "VuePress Blog Theme",
    "image": "/img/screenshots/meteorlxy-1.jpeg",
    "github": "https://github.com/meteorlxy/vuepress-theme-meteorlxy",
    "link": "https://vuepress-theme-meteorlxy.meteorlxy.cn/",
    "screenShots": [
      "/img/screenshots/meteorlxy-1.jpeg",
      "/img/screenshots/meteorlxy-2.jpeg",
      "/img/screenshots/meteorlxy-3.jpeg"
    ]
  },
  {
    "id": "7",
    "name": "simple",
    "type": "blog",
    "description": "Very Simple Blog Theme for VuePress",
    "image": "/img/screenshots/simple-1.jpeg",
    "github": "https://github.com/simple/vuepress-theme-simple",
    "link": "https://vuepress-theme-simple.simple.cn/",
    "screenShots": [
      "/img/screenshots/simple-1.jpeg",
      "/img/screenshots/simple-2.jpeg"
    ]
  },
  {
    "id": "8",
    "name": "portfolio",
    "type": "others",
    "description": "VuePress site with portfolio and blogging pages ready to deploy, and configured for Forestry",
    "image": "/img/screenshots/portfolio.jpeg",
    "github": "https://github.com/forestryio/portfolio-vuepress",
    "link": "https://vuepress-portfolio.netlify.com/",
    "screenShots": [
      "/img/screenshots/portfolio.jpeg"
    ]
  },
  {
    "id": "9",
    "name": "API",
    "type": "docs",
    "description": "An api-friendly theme for VuePress.",
    "image": "/img/screenshots/api.jpeg",
    "github": "https://github.com/sqrthree/vuepress-theme-api",
    "link": "https://blog.sqrtthree.com/vuepress-theme-api/",
    "screenShots": [
      "/img/screenshots/api.jpeg"
    ]
  },
  {
    "id": "10",
    "name": "ktquez",
    "type": "blog",
    "description": "A blog theme for VuePress by Ktquez.",
    "image": "/img/screenshots/ktquez-1.jpeg",
    "github": "https://github.com/ktquez/vuepress-theme-ktquez",
    "link": "https://ktquez-play.web.app/en/",
    "screenShots": [
      "/img/screenshots/ktquez-1.jpeg",
      "/img/screenshots/ktquez-2.jpeg",
      "/img/screenshots/ktquez-3.jpeg",
      "/img/screenshots/ktquez-4.jpeg"
    ]
  },
  {
    "id": "11",
    "name": "ououe",
    "type": "blog",
    "description": "A blog theme for VuePress by Ououe.",
    "image": "/img/screenshots/ououe-5.jpeg",
    "github": "https://github.com/tolking/vuepress-theme-ououe",
    "link": "https://ououe.com/",
    "screenShots": [
      "/img/screenshots/ououe-1.jpeg",
      "/img/screenshots/ououe-2.jpeg",
      "/img/screenshots/ououe-3.jpeg",
      "/img/screenshots/ououe-4.jpeg",
      "/img/screenshots/ououe-5.jpeg"
    ]
  },
  {
    "id": "12",
    "name": "yuicer",
    "type": "blog",
    "description": "A blog theme for VuePress by yuicer.",
    "image": "/img/screenshots/yuicer-1.jpeg",
    "github": "https://github.com/yuicer/vuepress-theme-yuicer",
    "link": "https://blog.yuicer.com",
    "screenShots": [
      "/img/screenshots/yuicer-1.jpeg",
      "/img/screenshots/yuicer-2.jpeg"
    ]
  },
  {
    "id": "13",
    "name": "resume",
    "type": "others",
    "description": "A resume vuepress theme By Wannaxiao",
    "image": "/img/screenshots/resume-1.jpeg",
    "github": "https://github.com/wannaxiao/vuepress-theme-resume",
    "link": "https://wannaxiao.github.io/vuepress-theme-resume/example/dist/",
    "screenShots": [
      "/img/screenshots/resume-1.jpeg"
    ]
  },
  {
    "id": "14",
    "name": "default prefers color scheme",
    "type": "docs",
    "description": "add prefers-color-scheme for vuepress default theme.",
    "image": "/img/screenshots/color-scheme-1.jpeg",
    "github": "https://github.com/tolking/vuepress-theme-default-prefers-color-scheme",
    "link": "https://tolking.github.io/vuepress-theme-default-prefers-color-scheme/",
    "screenShots": [
      "/img/screenshots/color-scheme-1.jpeg",
      "/img/screenshots/color-scheme-2.jpeg"
    ]
  },
  {
    "id": "15",
    "name": "yur",
    "type": "blog",
    "description": "A simple, powerful vuepress blog theme",
    "image": "/img/screenshots/yur-1.jpeg",
    "github": "https://github.com/cnguu/vuepress-theme-yur",
    "link": "https://gleehub.com/",
    "screenShots": [
      "/img/screenshots/yur-1.jpeg",
      "/img/screenshots/yur-2.jpeg",
      "/img/screenshots/yur-3.jpeg",
      "/img/screenshots/yur-4.jpeg",
      "/img/screenshots/yur-5.jpeg",
      "/img/screenshots/yur-6.jpeg",
      "/img/screenshots/yur-7.jpeg"
    ]
  }
]